{
  "states": [
    {
      "timestamp": "1636738760.0401592", 
      "value": {
        "eventName": "Actuator_RightArm", 
        "message": {
          "actuatorId": "dYV1Vt", 
          "sensorId": "ara", 
          "rawValue": null, 
          "value": 79.64113352318442, 
          "created": "2021-12-20T22:28:09.6056693Z"
        }
      }
    }, 
    {
      "timestamp": "1636738760.0401592", 
      "value": {
        "eventName": "Actuator_LeftArm", 
        "message": {
          "actuatorId": "NBQEA0", 
          "sensorId": "ala", 
          "rawValue": null, 
          "value": 80.21409131831524, 
          "created": "2021-12-20T22:28:09.6056693Z"
        }
      }
    }, 
    {
      "timestamp": "1636738760.0401592", 
      "value": {
        "eventName": "Actuator_HeadPitch", 
        "message": {
          "actuatorId": "Awb61F", 
          "sensorId": "ahp", 
          "rawValue": null, 
          "value": 1.7188733853924696, 
          "created": "2021-12-20T22:28:09.6056693Z"
        }
      }
    }, 
    {
      "timestamp": "1636738760.0401592", 
      "value": {
        "eventName": "Actuator_HeadRoll", 
        "message": {
          "actuatorId": "QSygCx", 
          "sensorId": "ahr", 
          "rawValue": null, 
          "value": 1.1459155902616465, 
          "created": "2021-12-20T22:28:09.6056693Z"
        }
      }
    }, 
    {
      "timestamp": "1636738760.0401592", 
      "value": {
        "eventName": "Actuator_HeadYaw", 
        "message": {
          "actuatorId": "2ABzJD", 
          "sensorId": "ahy", 
          "rawValue": null, 
          "value": 0.0, 
          "created": "2021-12-20T22:28:09.6056693Z"
        }
      }
    }, 
    {
      "timestamp": "1636738760.0401592", 
      "value": {
        "eventName": "/Sensors/RTC/IMU", 
        "message": {
          "created": "2021-12-20T22:28:09.6056693Z", 
          "xAcceleration": 0.13, 
          "yaw": 239.09528790809253, 
          "zAcceleration": -9.8, 
          "yawVelocity": 0.0, 
          "yAcceleration": -0.24, 
          "pitch": 1.3750987083139758, 
          "rollVelocity": 0.0, 
          "sensorId": "imu", 
          "pitchVelocity": 0.0, 
          "roll": 0.7448451336700703
        }
      }
    }, 
    {
      "timestamp": "1636738760.0401592", 
      "value": {
        "eventName": "Actuator_RightArm", 
        "message": {
          "actuatorId": "dYV1Vt", 
          "sensorId": "ara", 
          "rawValue": null, 
          "value": 79.64113352318442, 
          "created": "2021-12-20T22:28:09.7629488Z"
        }
      }
    }, 
    {
      "timestamp": "1636738760.0401592", 
      "value": {
        "eventName": "Actuator_LeftArm", 
        "message": {
          "actuatorId": "NBQEA0", 
          "sensorId": "ala", 
          "rawValue": null, 
          "value": 80.21409131831524, 
          "created": "2021-12-20T22:28:09.7629488Z"
        }
      }
    }, 
    {
      "timestamp": "1636738760.0401592", 
      "value": {
        "eventName": "Actuator_HeadPitch", 
        "message": {
          "actuatorId": "Awb61F", 
          "sensorId": "ahp", 
          "rawValue": null, 
          "value": 1.1459155902616465, 
          "created": "2021-12-20T22:28:09.7629488Z"
        }
      }
    }, 
    {
      "timestamp": "1636738760.0401592", 
      "value": {
        "eventName": "Actuator_HeadRoll", 
        "message": {
          "actuatorId": "QSygCx", 
          "sensorId": "ahr", 
          "rawValue": null, 
          "value": 1.1459155902616465, 
          "created": "2021-12-20T22:28:09.7629488Z"
        }
      }
    }, 
    {
      "timestamp": "1636738760.0401592", 
      "value": {
        "eventName": "Actuator_HeadYaw", 
        "message": {
          "actuatorId": "2ABzJD", 
          "sensorId": "ahy", 
          "rawValue": null, 
          "value": 0.0, 
          "created": "2021-12-20T22:28:09.7629488Z"
        }
      }
    }, 
    {
      "timestamp": "1636738760.0401592", 
      "value": {
        "eventName": "/Sensors/RTC/IMU", 
        "message": {
          "created": "2021-12-20T22:28:09.7785742Z", 
          "xAcceleration": 0.13, 
          "yaw": 239.09528790809253, 
          "zAcceleration": -9.8, 
          "yawVelocity": 0.0, 
          "yAcceleration": -0.24, 
          "pitch": 1.3750987083139758, 
          "rollVelocity": 0.0, 
          "sensorId": "imu", 
          "pitchVelocity": 0.0, 
          "roll": 0.7448451336700703
        }
      }
    }, 
    {
      "timestamp": "1636738760.0401592", 
      "value": {
        "eventName": "Actuator_RightArm", 
        "message": {
          "actuatorId": "dYV1Vt", 
          "sensorId": "ara", 
          "rawValue": null, 
          "value": 79.64113352318442, 
          "created": "2021-12-20T22:28:09.9843377Z"
        }
      }
    }, 
    {
      "timestamp": "1636738760.0401592", 
      "value": {
        "eventName": "Actuator_LeftArm", 
        "message": {
          "actuatorId": "NBQEA0", 
          "sensorId": "ala", 
          "rawValue": null, 
          "value": 80.21409131831524, 
          "created": "2021-12-20T22:28:09.9843377Z"
        }
      }
    }, 
    {
      "timestamp": "1636738760.0401592", 
      "value": {
        "eventName": "Actuator_HeadPitch", 
        "message": {
          "actuatorId": "Awb61F", 
          "sensorId": "ahp", 
          "rawValue": null, 
          "value": 1.7188733853924696, 
          "created": "2021-12-20T22:28:09.9843377Z"
        }
      }
    }, 
    {
      "timestamp": "1636738760.0401592", 
      "value": {
        "eventName": "Actuator_HeadRoll", 
        "message": {
          "actuatorId": "QSygCx", 
          "sensorId": "ahr", 
          "rawValue": null, 
          "value": 1.1459155902616465, 
          "created": "2021-12-20T22:28:09.9843377Z"
        }
      }
    }, 
    {
      "timestamp": "1636738760.0401592", 
      "value": {
        "eventName": "Actuator_HeadYaw", 
        "message": {
          "actuatorId": "2ABzJD", 
          "sensorId": "ahy", 
          "rawValue": null, 
          "value": 0.0, 
          "created": "2021-12-20T22:28:09.9843377Z"
        }
      }
    }, 
    {
      "timestamp": "1636738760.0401592", 
      "value": {
        "eventName": "/Sensors/RTC/IMU", 
        "message": {
          "created": "2021-12-20T22:28:09.9843377Z", 
          "xAcceleration": 0.13, 
          "yaw": 239.09528790809253, 
          "zAcceleration": -9.8, 
          "yawVelocity": 0.0, 
          "yAcceleration": -0.24, 
          "pitch": 1.3750987083139758, 
          "rollVelocity": 0.0, 
          "sensorId": "imu", 
          "pitchVelocity": 0.11459155902616464, 
          "roll": 0.7448451336700703
        }
      }
    }, 
    {
      "timestamp": "1636738760.0401592", 
      "value": {
        "eventName": "/Sensors/RTC/IMU", 
        "message": {
          "created": "2021-12-20T22:28:10.1843924Z", 
          "xAcceleration": 0.13, 
          "yaw": 239.09528790809253, 
          "zAcceleration": -9.8, 
          "yawVelocity": -0.11459155902616464, 
          "yAcceleration": -0.24, 
          "pitch": 1.3750987083139758, 
          "rollVelocity": 0.0, 
          "sensorId": "imu", 
          "pitchVelocity": 0.0, 
          "roll": 0.7448451336700703
        }
      }
    }, 
    {
      "timestamp": "1636738760.0401592", 
      "value": {
        "eventName": "Actuator_RightArm", 
        "message": {
          "actuatorId": "dYV1Vt", 
          "sensorId": "ara", 
          "rawValue": null, 
          "value": 79.64113352318442, 
          "created": "2021-12-20T22:28:10.1843924Z"
        }
      }
    }, 
    {
      "timestamp": "1636738760.0401592", 
      "value": {
        "eventName": "Actuator_LeftArm", 
        "message": {
          "actuatorId": "NBQEA0", 
          "sensorId": "ala", 
          "rawValue": null, 
          "value": 80.21409131831524, 
          "created": "2021-12-20T22:28:10.1843924Z"
        }
      }
    }, 
    {
      "timestamp": "1636738760.0401592", 
      "value": {
        "eventName": "Actuator_HeadPitch", 
        "message": {
          "actuatorId": "Awb61F", 
          "sensorId": "ahp", 
          "rawValue": null, 
          "value": 1.7188733853924696, 
          "created": "2021-12-20T22:28:10.1843924Z"
        }
      }
    }, 
    {
      "timestamp": "1636738760.0401592", 
      "value": {
        "eventName": "Actuator_HeadRoll", 
        "message": {
          "actuatorId": "QSygCx", 
          "sensorId": "ahr", 
          "rawValue": null, 
          "value": 1.1459155902616465, 
          "created": "2021-12-20T22:28:10.1843924Z"
        }
      }
    }, 
    {
      "timestamp": "1636738760.0401592", 
      "value": {
        "eventName": "Actuator_HeadYaw", 
        "message": {
          "actuatorId": "2ABzJD", 
          "sensorId": "ahy", 
          "rawValue": null, 
          "value": -4.583662361046586, 
          "created": "2021-12-20T22:28:10.2000616Z"
        }
      }
    }, 
    {
      "timestamp": "1636738760.0401592", 
      "value": {
        "eventName": "/Sensors/RTC/IMU", 
        "message": {
          "created": "2021-12-20T22:28:10.2938708Z", 
          "xAcceleration": 0.13, 
          "yaw": 239.09528790809253, 
          "zAcceleration": -9.8, 
          "yawVelocity": 0.0, 
          "yAcceleration": -0.24, 
          "pitch": 1.3750987083139758, 
          "rollVelocity": 0.0, 
          "sensorId": "imu", 
          "pitchVelocity": 0.05729577951308232, 
          "roll": 0.7448451336700703
        }
      }
    }, 
    {
      "timestamp": "1636738760.0401592", 
      "value": {
        "eventName": "Actuator_RightArm", 
        "message": {
          "actuatorId": "dYV1Vt", 
          "sensorId": "ara", 
          "rawValue": null, 
          "value": 79.64113352318442, 
          "created": "2021-12-20T22:28:10.4032614Z"
        }
      }
    }, 
    {
      "timestamp": "1636738760.0401592", 
      "value": {
        "eventName": "Actuator_LeftArm", 
        "message": {
          "actuatorId": "NBQEA0", 
          "sensorId": "ala", 
          "rawValue": null, 
          "value": 75.63042895726868, 
          "created": "2021-12-20T22:28:10.4032614Z"
        }
      }
    }, 
    {
      "timestamp": "1636738760.0401592", 
      "value": {
        "eventName": "Actuator_HeadPitch", 
        "message": {
          "actuatorId": "Awb61F", 
          "sensorId": "ahp", 
          "rawValue": null, 
          "value": 0.0, 
          "created": "2021-12-20T22:28:10.4032614Z"
        }
      }
    }, 
    {
      "timestamp": "1636738760.0401592", 
      "value": {
        "eventName": "Actuator_HeadRoll", 
        "message": {
          "actuatorId": "QSygCx", 
          "sensorId": "ahr", 
          "rawValue": null, 
          "value": -0.5729577951308232, 
          "created": "2021-12-20T22:28:10.4032614Z"
        }
      }
    }, 
    {
      "timestamp": "1636738760.0401592", 
      "value": {
        "eventName": "Actuator_HeadYaw", 
        "message": {
          "actuatorId": "2ABzJD", 
          "sensorId": "ahy", 
          "rawValue": null, 
          "value": -7.448451336700702, 
          "created": "2021-12-20T22:28:10.4032614Z"
        }
      }
    }, 
    {
      "timestamp": "1636738760.0401592", 
      "value": {
        "eventName": "/Sensors/RTC/IMU", 
        "message": {
          "created": "2021-12-20T22:28:10.4814862Z", 
          "xAcceleration": 0.13, 
          "yaw": 239.09528790809253, 
          "zAcceleration": -9.8, 
          "yawVelocity": 0.0, 
          "yAcceleration": -0.24, 
          "pitch": 1.3750987083139758, 
          "rollVelocity": 0.0, 
          "sensorId": "imu", 
          "pitchVelocity": 0.8594366926962348, 
          "roll": 0.7448451336700703
        }
      }
    }, 
    {
      "timestamp": "1636738760.0401592", 
      "value": {
        "eventName": "Actuator_RightArm", 
        "message": {
          "actuatorId": "dYV1Vt", 
          "sensorId": "ara", 
          "rawValue": null, 
          "value": 79.64113352318442, 
          "created": "2021-12-20T22:28:10.5759746Z"
        }
      }
    }, 
    {
      "timestamp": "1636738760.0401592", 
      "value": {
        "eventName": "Actuator_LeftArm", 
        "message": {
          "actuatorId": "NBQEA0", 
          "sensorId": "ala", 
          "rawValue": null, 
          "value": 73.9115555718762, 
          "created": "2021-12-20T22:28:10.5759746Z"
        }
      }
    }, 
    {
      "timestamp": "1636738760.0401592", 
      "value": {
        "eventName": "Actuator_HeadPitch", 
        "message": {
          "actuatorId": "Awb61F", 
          "sensorId": "ahp", 
          "rawValue": null, 
          "value": -2.291831180523293, 
          "created": "2021-12-20T22:28:10.591595Z"
        }
      }
    }, 
    {
      "timestamp": "1636738760.0401592", 
      "value": {
        "eventName": "Actuator_HeadRoll", 
        "message": {
          "actuatorId": "QSygCx", 
          "sensorId": "ahr", 
          "rawValue": null, 
          "value": -4.583662361046586, 
          "created": "2021-12-20T22:28:10.591595Z"
        }
      }
    }, 
    {
      "timestamp": "1636738760.0401592", 
      "value": {
        "eventName": "Actuator_HeadYaw", 
        "message": {
          "actuatorId": "2ABzJD", 
          "sensorId": "ahy", 
          "rawValue": null, 
          "value": -10.313240312354818, 
          "created": "2021-12-20T22:28:10.591595Z"
        }
      }
    }, 
    {
      "timestamp": "1636738760.0401592", 
      "value": {
        "eventName": "/Sensors/RTC/IMU", 
        "message": {
          "created": "2021-12-20T22:28:10.6544197Z", 
          "xAcceleration": 0.13, 
          "yaw": 239.09528790809253, 
          "zAcceleration": -9.8, 
          "yawVelocity": 0.0, 
          "yAcceleration": -0.24, 
          "pitch": 1.3750987083139758, 
          "rollVelocity": 0.05729577951308232, 
          "sensorId": "imu", 
          "pitchVelocity": 0.0, 
          "roll": 0.7448451336700703
        }
      }
    }, 
    {
      "timestamp": "1636738760.0401592", 
      "value": {
        "eventName": "Actuator_RightArm", 
        "message": {
          "actuatorId": "dYV1Vt", 
          "sensorId": "ara", 
          "rawValue": null, 
          "value": 79.64113352318442, 
          "created": "2021-12-20T22:28:10.7953035Z"
        }
      }
    }, 
    {
      "timestamp": "1636738760.0401592", 
      "value": {
        "eventName": "Actuator_LeftArm", 
        "message": {
          "actuatorId": "NBQEA0", 
          "sensorId": "ala", 
          "rawValue": null, 
          "value": 73.9115555718762, 
          "created": "2021-12-20T22:28:10.7953035Z"
        }
      }
    }, 
    {
      "timestamp": "1636738760.0401592", 
      "value": {
        "eventName": "Actuator_HeadPitch", 
        "message": {
          "actuatorId": "Awb61F", 
          "sensorId": "ahp", 
          "rawValue": null, 
          "value": -3.437746770784939, 
          "created": "2021-12-20T22:28:10.7953035Z"
        }
      }
    }, 
    {
      "timestamp": "1636738760.0401592", 
      "value": {
        "eventName": "Actuator_HeadRoll", 
        "message": {
          "actuatorId": "QSygCx", 
          "sensorId": "ahr", 
          "rawValue": null, 
          "value": -8.021409131831525, 
          "created": "2021-12-20T22:28:10.7953035Z"
        }
      }
    }, 
    {
      "timestamp": "1636738760.0401592", 
      "value": {
        "eventName": "Actuator_HeadYaw", 
        "message": {
          "actuatorId": "2ABzJD", 
          "sensorId": "ahy", 
          "rawValue": null, 
          "value": -13.178029288008934, 
          "created": "2021-12-20T22:28:10.7953035Z"
        }
      }
    }, 
    {
      "timestamp": "1636738760.0401592", 
      "value": {
        "eventName": "/Sensors/RTC/IMU", 
        "message": {
          "created": "2021-12-20T22:28:10.8267663Z", 
          "xAcceleration": 0.13, 
          "yaw": 239.09528790809253, 
          "zAcceleration": -9.8, 
          "yawVelocity": 0.0, 
          "yAcceleration": -0.24, 
          "pitch": 1.3750987083139758, 
          "rollVelocity": 0.0, 
          "sensorId": "imu", 
          "pitchVelocity": -0.2864788975654116, 
          "roll": 0.7448451336700703
        }
      }
    }, 
    {
      "timestamp": "1636738760.0401592", 
      "value": {
        "eventName": "Actuator_RightArm", 
        "message": {
          "actuatorId": "dYV1Vt", 
          "sensorId": "ara", 
          "rawValue": null, 
          "value": 79.64113352318442, 
          "created": "2021-12-20T22:28:10.9716139Z"
        }
      }
    }, 
    {
      "timestamp": "1636738760.0401592", 
      "value": {
        "eventName": "Actuator_LeftArm", 
        "message": {
          "actuatorId": "NBQEA0", 
          "sensorId": "ala", 
          "rawValue": null, 
          "value": 73.9115555718762, 
          "created": "2021-12-20T22:28:10.9716139Z"
        }
      }
    }, 
    {
      "timestamp": "1636738760.0401592", 
      "value": {
        "eventName": "Actuator_HeadPitch", 
        "message": {
          "actuatorId": "Awb61F", 
          "sensorId": "ahp", 
          "rawValue": null, 
          "value": -4.583662361046586, 
          "created": "2021-12-20T22:28:10.9716139Z"
        }
      }
    }, 
    {
      "timestamp": "1636738760.0401592", 
      "value": {
        "eventName": "Actuator_HeadRoll", 
        "message": {
          "actuatorId": "QSygCx", 
          "sensorId": "ahr", 
          "rawValue": null, 
          "value": -9.167324722093172, 
          "created": "2021-12-20T22:28:10.9716139Z"
        }
      }
    }, 
    {
      "timestamp": "1636738760.0401592", 
      "value": {
        "eventName": "Actuator_HeadYaw", 
        "message": {
          "actuatorId": "2ABzJD", 
          "sensorId": "ahy", 
          "rawValue": null, 
          "value": -16.04281826366305, 
          "created": "2021-12-20T22:28:10.9716139Z"
        }
      }
    }, 
    {
      "timestamp": "1636738760.0401592", 
      "value": {
        "eventName": "/Sensors/RTC/IMU", 
        "message": {
          "created": "2021-12-20T22:28:11.0029602Z", 
          "xAcceleration": 0.13, 
          "yaw": 239.09528790809253, 
          "zAcceleration": -9.8, 
          "yawVelocity": 0.0, 
          "yAcceleration": -0.24, 
          "pitch": 1.3750987083139758, 
          "rollVelocity": -0.05729577951308232, 
          "sensorId": "imu", 
          "pitchVelocity": 0.40107045659157625, 
          "roll": 0.7448451336700703
        }
      }
    }, 
    {
      "timestamp": "1636738760.0401592", 
      "value": {
        "eventName": "Actuator_RightArm", 
        "message": {
          "actuatorId": "dYV1Vt", 
          "sensorId": "ara", 
          "rawValue": null, 
          "value": 79.64113352318442, 
          "created": "2021-12-20T22:28:11.4269184Z"
        }
      }
    }, 
    {
      "timestamp": "1636738760.0401592", 
      "value": {
        "eventName": "Actuator_LeftArm", 
        "message": {
          "actuatorId": "NBQEA0", 
          "sensorId": "ala", 
          "rawValue": null, 
          "value": 73.9115555718762, 
          "created": "2021-12-20T22:28:11.4269184Z"
        }
      }
    }, 
    {
      "timestamp": "1636738760.0401592", 
      "value": {
        "eventName": "Actuator_HeadPitch", 
        "message": {
          "actuatorId": "Awb61F", 
          "sensorId": "ahp", 
          "rawValue": null, 
          "value": -5.729577951308232, 
          "created": "2021-12-20T22:28:11.4269184Z"
        }
      }
    }, 
    {
      "timestamp": "1636738760.0401592", 
      "value": {
        "eventName": "Actuator_HeadRoll", 
        "message": {
          "actuatorId": "QSygCx", 
          "sensorId": "ahr", 
          "rawValue": null, 
          "value": -11.459155902616464, 
          "created": "2021-12-20T22:28:11.4269184Z"
        }
      }
    }, 
    {
      "timestamp": "1636738760.0401592", 
      "value": {
        "eventName": "Actuator_HeadYaw", 
        "message": {
          "actuatorId": "2ABzJD", 
          "sensorId": "ahy", 
          "rawValue": null, 
          "value": -18.90760723931717, 
          "created": "2021-12-20T22:28:11.4269184Z"
        }
      }
    }, 
    {
      "timestamp": "1636738760.0401592", 
      "value": {
        "eventName": "/Sensors/RTC/IMU", 
        "message": {
          "created": "2021-12-20T22:28:11.4269184Z", 
          "xAcceleration": 0.13, 
          "yaw": 239.09528790809253, 
          "zAcceleration": -9.8, 
          "yawVelocity": 0.0, 
          "yAcceleration": -0.24, 
          "pitch": 1.3750987083139758, 
          "rollVelocity": 0.0, 
          "sensorId": "imu", 
          "pitchVelocity": -0.40107045659157625, 
          "roll": 0.7448451336700703
        }
      }
    }, 
    {
      "timestamp": "1636738760.0401592", 
      "value": {
        "eventName": "Actuator_RightArm", 
        "message": {
          "actuatorId": "dYV1Vt", 
          "sensorId": "ara", 
          "rawValue": null, 
          "value": 79.64113352318442, 
          "created": "2021-12-20T22:28:11.5560083Z"
        }
      }
    }, 
    {
      "timestamp": "1636738760.0401592", 
      "value": {
        "eventName": "Actuator_LeftArm", 
        "message": {
          "actuatorId": "NBQEA0", 
          "sensorId": "ala", 
          "rawValue": null, 
          "value": 73.9115555718762, 
          "created": "2021-12-20T22:28:11.5560083Z"
        }
      }
    }, 
    {
      "timestamp": "1636738760.0401592", 
      "value": {
        "eventName": "Actuator_HeadPitch", 
        "message": {
          "actuatorId": "Awb61F", 
          "sensorId": "ahp", 
          "rawValue": null, 
          "value": -8.021409131831525, 
          "created": "2021-12-20T22:28:11.5560083Z"
        }
      }
    }, 
    {
      "timestamp": "1636738760.0401592", 
      "value": {
        "eventName": "Actuator_HeadRoll", 
        "message": {
          "actuatorId": "QSygCx", 
          "sensorId": "ahr", 
          "rawValue": null, 
          "value": -15.469860468532227, 
          "created": "2021-12-20T22:28:11.5560083Z"
        }
      }
    }, 
    {
      "timestamp": "1636738760.0401592", 
      "value": {
        "eventName": "Actuator_HeadYaw", 
        "message": {
          "actuatorId": "2ABzJD", 
          "sensorId": "ahy", 
          "rawValue": null, 
          "value": -24.637185190625402, 
          "created": "2021-12-20T22:28:11.5560083Z"
        }
      }
    }, 
    {
      "timestamp": "1636738760.0401592", 
      "value": {
        "eventName": "/Sensors/RTC/IMU", 
        "message": {
          "created": "2021-12-20T22:28:11.6972376Z", 
          "xAcceleration": 0.13, 
          "yaw": 239.09528790809253, 
          "zAcceleration": -9.8, 
          "yawVelocity": 0.0, 
          "yAcceleration": -0.24, 
          "pitch": 1.3750987083139758, 
          "rollVelocity": 0.11459155902616464, 
          "sensorId": "imu", 
          "pitchVelocity": 0.0, 
          "roll": 0.7448451336700703
        }
      }
    }, 
    {
      "timestamp": "1636738760.0401592", 
      "value": {
        "eventName": "Actuator_RightArm", 
        "message": {
          "actuatorId": "dYV1Vt", 
          "sensorId": "ara", 
          "rawValue": null, 
          "value": 79.64113352318442, 
          "created": "2021-12-20T22:28:11.7443331Z"
        }
      }
    }, 
    {
      "timestamp": "1636738760.0401592", 
      "value": {
        "eventName": "Actuator_LeftArm", 
        "message": {
          "actuatorId": "NBQEA0", 
          "sensorId": "ala", 
          "rawValue": null, 
          "value": 73.9115555718762, 
          "created": "2021-12-20T22:28:11.7443331Z"
        }
      }
    }, 
    {
      "timestamp": "1636738760.0401592", 
      "value": {
        "eventName": "Actuator_HeadPitch", 
        "message": {
          "actuatorId": "Awb61F", 
          "sensorId": "ahp", 
          "rawValue": null, 
          "value": -9.167324722093172, 
          "created": "2021-12-20T22:28:11.7443331Z"
        }
      }
    }, 
    {
      "timestamp": "1636738760.0401592", 
      "value": {
        "eventName": "Actuator_HeadRoll", 
        "message": {
          "actuatorId": "QSygCx", 
          "sensorId": "ahr", 
          "rawValue": null, 
          "value": -17.188733853924695, 
          "created": "2021-12-20T22:28:11.7443331Z"
        }
      }
    }, 
    {
      "timestamp": "1636738760.0401592", 
      "value": {
        "eventName": "Actuator_HeadYaw", 
        "message": {
          "actuatorId": "2ABzJD", 
          "sensorId": "ahy", 
          "rawValue": null, 
          "value": -28.07493196141034, 
          "created": "2021-12-20T22:28:11.7443331Z"
        }
      }
    }, 
    {
      "timestamp": "1636738760.0401592", 
      "value": {
        "eventName": "/Sensors/RTC/IMU", 
        "message": {
          "created": "2021-12-20T22:28:11.9163349Z", 
          "xAcceleration": 0.13, 
          "yaw": 239.09528790809253, 
          "zAcceleration": -9.8, 
          "yawVelocity": -0.17188733853924698, 
          "yAcceleration": -0.24, 
          "pitch": 1.3750987083139758, 
          "rollVelocity": -0.05729577951308232, 
          "sensorId": "imu", 
          "pitchVelocity": 0.0, 
          "roll": 0.7448451336700703
        }
      }
    }, 
    {
      "timestamp": "1636738760.0401592", 
      "value": {
        "eventName": "Actuator_RightArm", 
        "message": {
          "actuatorId": "dYV1Vt", 
          "sensorId": "ara", 
          "rawValue": null, 
          "value": 79.64113352318442, 
          "created": "2021-12-20T22:28:11.9632461Z"
        }
      }
    }, 
    {
      "timestamp": "1636738760.0401592", 
      "value": {
        "eventName": "Actuator_LeftArm", 
        "message": {
          "actuatorId": "NBQEA0", 
          "sensorId": "ala", 
          "rawValue": null, 
          "value": 73.9115555718762, 
          "created": "2021-12-20T22:28:11.9632461Z"
        }
      }
    }, 
    {
      "timestamp": "1636738760.0401592", 
      "value": {
        "eventName": "Actuator_HeadPitch", 
        "message": {
          "actuatorId": "Awb61F", 
          "sensorId": "ahp", 
          "rawValue": null, 
          "value": -9.740282517223996, 
          "created": "2021-12-20T22:28:11.9632461Z"
        }
      }
    }, 
    {
      "timestamp": "1636738760.0401592", 
      "value": {
        "eventName": "Actuator_HeadRoll", 
        "message": {
          "actuatorId": "QSygCx", 
          "sensorId": "ahr", 
          "rawValue": null, 
          "value": -18.90760723931717, 
          "created": "2021-12-20T22:28:11.9632461Z"
        }
      }
    }, 
    {
      "timestamp": "1636738760.0401592", 
      "value": {
        "eventName": "Actuator_HeadYaw", 
        "message": {
          "actuatorId": "2ABzJD", 
          "sensorId": "ahy", 
          "rawValue": null, 
          "value": -30.939720937064454, 
          "created": "2021-12-20T22:28:11.9632461Z"
        }
      }
    }, 
    {
      "timestamp": "1636738760.0401592", 
      "value": {
        "eventName": "/Sensors/RTC/IMU", 
        "message": {
          "created": "2021-12-20T22:28:12.0417148Z", 
          "xAcceleration": 0.13, 
          "yaw": 239.09528790809253, 
          "zAcceleration": -9.8, 
          "yawVelocity": -0.17188733853924698, 
          "yAcceleration": -0.24, 
          "pitch": 1.3750987083139758, 
          "rollVelocity": 0.0, 
          "sensorId": "imu", 
          "pitchVelocity": -0.40107045659157625, 
          "roll": 0.7448451336700703
        }
      }
    }, 
    {
      "timestamp": "1636738760.0401592", 
      "value": {
        "eventName": "Actuator_RightArm", 
        "message": {
          "actuatorId": "dYV1Vt", 
          "sensorId": "ara", 
          "rawValue": null, 
          "value": 79.64113352318442, 
          "created": "2021-12-20T22:28:12.1834117Z"
        }
      }
    }, 
    {
      "timestamp": "1636738760.0401592", 
      "value": {
        "eventName": "Actuator_LeftArm", 
        "message": {
          "actuatorId": "NBQEA0", 
          "sensorId": "ala", 
          "rawValue": null, 
          "value": 73.9115555718762, 
          "created": "2021-12-20T22:28:12.1834117Z"
        }
      }
    }, 
    {
      "timestamp": "1636738760.0401592", 
      "value": {
        "eventName": "Actuator_HeadPitch", 
        "message": {
          "actuatorId": "Awb61F", 
          "sensorId": "ahp", 
          "rawValue": null, 
          "value": -8.021409131831525, 
          "created": "2021-12-20T22:28:12.1834117Z"
        }
      }
    }, 
    {
      "timestamp": "1636738760.0401592", 
      "value": {
        "eventName": "Actuator_HeadRoll", 
        "message": {
          "actuatorId": "QSygCx", 
          "sensorId": "ahr", 
          "rawValue": null, 
          "value": -18.334649444186343, 
          "created": "2021-12-20T22:28:12.1834117Z"
        }
      }
    }, 
    {
      "timestamp": "1636738760.0401592", 
      "value": {
        "eventName": "Actuator_HeadYaw", 
        "message": {
          "actuatorId": "2ABzJD", 
          "sensorId": "ahy", 
          "rawValue": null, 
          "value": -30.939720937064454, 
          "created": "2021-12-20T22:28:12.1834117Z"
        }
      }
    }, 
    {
      "timestamp": "1636738760.0401592", 
      "value": {
        "eventName": "/Sensors/RTC/IMU", 
        "message": {
          "created": "2021-12-20T22:28:12.2150204Z", 
          "xAcceleration": 0.13, 
          "yaw": 239.09528790809253, 
          "zAcceleration": -9.8, 
          "yawVelocity": 0.0, 
          "yAcceleration": -0.24, 
          "pitch": 1.3750987083139758, 
          "rollVelocity": 0.0, 
          "sensorId": "imu", 
          "pitchVelocity": -0.45836623610465854, 
          "roll": 0.7448451336700703
        }
      }
    }, 
    {
      "timestamp": "1636738760.0401592", 
      "value": {
        "eventName": "Actuator_RightArm", 
        "message": {
          "actuatorId": "dYV1Vt", 
          "sensorId": "ara", 
          "rawValue": null, 
          "value": 79.64113352318442, 
          "created": "2021-12-20T22:28:12.3415827Z"
        }
      }
    }, 
    {
      "timestamp": "1636738760.0401592", 
      "value": {
        "eventName": "Actuator_LeftArm", 
        "message": {
          "actuatorId": "NBQEA0", 
          "sensorId": "ala", 
          "rawValue": null, 
          "value": 73.9115555718762, 
          "created": "2021-12-20T22:28:12.3572188Z"
        }
      }
    }, 
    {
      "timestamp": "1636738760.0401592", 
      "value": {
        "eventName": "Actuator_HeadPitch", 
        "message": {
          "actuatorId": "Awb61F", 
          "sensorId": "ahp", 
          "rawValue": null, 
          "value": -8.021409131831525, 
          "created": "2021-12-20T22:28:12.3572188Z"
        }
      }
    }, 
    {
      "timestamp": "1636738760.0401592", 
      "value": {
        "eventName": "Actuator_HeadRoll", 
        "message": {
          "actuatorId": "QSygCx", 
          "sensorId": "ahr", 
          "rawValue": null, 
          "value": -18.334649444186343, 
          "created": "2021-12-20T22:28:12.3572188Z"
        }
      }
    }, 
    {
      "timestamp": "1636738760.0401592", 
      "value": {
        "eventName": "Actuator_HeadYaw", 
        "message": {
          "actuatorId": "2ABzJD", 
          "sensorId": "ahy", 
          "rawValue": null, 
          "value": -27.501974166279513, 
          "created": "2021-12-20T22:28:12.3572188Z"
        }
      }
    }, 
    {
      "timestamp": "1636738760.0401592", 
      "value": {
        "eventName": "/Sensors/RTC/IMU", 
        "message": {
          "created": "2021-12-20T22:28:12.4066491Z", 
          "xAcceleration": 0.13, 
          "yaw": 239.09528790809253, 
          "zAcceleration": -9.8, 
          "yawVelocity": 0.0, 
          "yAcceleration": -0.24, 
          "pitch": 1.3750987083139758, 
          "rollVelocity": 0.11459155902616464, 
          "sensorId": "imu", 
          "pitchVelocity": -0.05729577951308232, 
          "roll": 0.7448451336700703
        }
      }
    }, 
    {
      "timestamp": "1636738760.0401592", 
      "value": {
        "eventName": "Actuator_RightArm", 
        "message": {
          "actuatorId": "dYV1Vt", 
          "sensorId": "ara", 
          "rawValue": null, 
          "value": 79.64113352318442, 
          "created": "2021-12-20T22:28:12.5795201Z"
        }
      }
    }, 
    {
      "timestamp": "1636738760.0401592", 
      "value": {
        "eventName": "Actuator_LeftArm", 
        "message": {
          "actuatorId": "NBQEA0", 
          "sensorId": "ala", 
          "rawValue": null, 
          "value": 80.21409131831524, 
          "created": "2021-12-20T22:28:12.5795201Z"
        }
      }
    }, 
    {
      "timestamp": "1636738760.0401592", 
      "value": {
        "eventName": "Actuator_HeadPitch", 
        "message": {
          "actuatorId": "Awb61F", 
          "sensorId": "ahp", 
          "rawValue": null, 
          "value": -8.021409131831525, 
          "created": "2021-12-20T22:28:12.5795201Z"
        }
      }
    }, 
    {
      "timestamp": "1636738760.0401592", 
      "value": {
        "eventName": "Actuator_HeadRoll", 
        "message": {
          "actuatorId": "QSygCx", 
          "sensorId": "ahr", 
          "rawValue": null, 
          "value": -18.334649444186343, 
          "created": "2021-12-20T22:28:12.5795201Z"
        }
      }
    }, 
    {
      "timestamp": "1636738760.0401592", 
      "value": {
        "eventName": "Actuator_HeadYaw", 
        "message": {
          "actuatorId": "2ABzJD", 
          "sensorId": "ahy", 
          "rawValue": null, 
          "value": -26.35605857601787, 
          "created": "2021-12-20T22:28:12.5951484Z"
        }
      }
    }, 
    {
      "timestamp": "1636738760.0401592", 
      "value": {
        "eventName": "/Sensors/RTC/IMU", 
        "message": {
          "created": "2021-12-20T22:28:12.5951484Z", 
          "xAcceleration": 0.13, 
          "yaw": 239.09528790809253, 
          "zAcceleration": -9.8, 
          "yawVelocity": 0.05729577951308232, 
          "yAcceleration": -0.24, 
          "pitch": 1.3750987083139758, 
          "rollVelocity": 0.05729577951308232, 
          "sensorId": "imu", 
          "pitchVelocity": 0.0, 
          "roll": 0.7448451336700703
        }
      }
    }, 
    {
      "timestamp": "1636738760.0401592", 
      "value": {
        "eventName": "/Sensors/RTC/IMU", 
        "message": {
          "created": "2021-12-20T22:28:12.7746994Z", 
          "xAcceleration": 0.13, 
          "yaw": 239.09528790809253, 
          "zAcceleration": -9.8, 
          "yawVelocity": 0.0, 
          "yAcceleration": -0.24, 
          "pitch": 1.3750987083139758, 
          "rollVelocity": -0.05729577951308232, 
          "sensorId": "imu", 
          "pitchVelocity": 0.0, 
          "roll": 0.7448451336700703
        }
      }
    }, 
    {
      "timestamp": "1636738760.0401592", 
      "value": {
        "eventName": "Actuator_RightArm", 
        "message": {
          "actuatorId": "dYV1Vt", 
          "sensorId": "ara", 
          "rawValue": null, 
          "value": 79.64113352318442, 
          "created": "2021-12-20T22:28:12.7746994Z"
        }
      }
    }, 
    {
      "timestamp": "1636738760.0401592", 
      "value": {
        "eventName": "Actuator_LeftArm", 
        "message": {
          "actuatorId": "NBQEA0", 
          "sensorId": "ala", 
          "rawValue": null, 
          "value": 80.78704911344607, 
          "created": "2021-12-20T22:28:12.7746994Z"
        }
      }
    }, 
    {
      "timestamp": "1636738760.0401592", 
      "value": {
        "eventName": "Actuator_HeadPitch", 
        "message": {
          "actuatorId": "Awb61F", 
          "sensorId": "ahp", 
          "rawValue": null, 
          "value": -8.021409131831525, 
          "created": "2021-12-20T22:28:12.7746994Z"
        }
      }
    }, 
    {
      "timestamp": "1636738760.0401592", 
      "value": {
        "eventName": "Actuator_HeadRoll", 
        "message": {
          "actuatorId": "QSygCx", 
          "sensorId": "ahr", 
          "rawValue": null, 
          "value": -18.334649444186343, 
          "created": "2021-12-20T22:28:12.7746994Z"
        }
      }
    }, 
    {
      "timestamp": "1636738760.0401592", 
      "value": {
        "eventName": "Actuator_HeadYaw", 
        "message": {
          "actuatorId": "2ABzJD", 
          "sensorId": "ahy", 
          "rawValue": null, 
          "value": -25.210142985756224, 
          "created": "2021-12-20T22:28:12.7746994Z"
        }
      }
    }, 
    {
      "timestamp": "1636738760.0401592", 
      "value": {
        "eventName": "/Sensors/RTC/IMU", 
        "message": {
          "created": "2021-12-20T22:28:12.9220706Z", 
          "xAcceleration": 0.13, 
          "yaw": 239.09528790809253, 
          "zAcceleration": -9.8, 
          "yawVelocity": 0.0, 
          "yAcceleration": -0.24, 
          "pitch": 1.3750987083139758, 
          "rollVelocity": 0.0, 
          "sensorId": "imu", 
          "pitchVelocity": 0.05729577951308232, 
          "roll": 0.7448451336700703
        }
      }
    }, 
    {
      "timestamp": "1636738760.0401592", 
      "value": {
        "eventName": "Actuator_RightArm", 
        "message": {
          "actuatorId": "dYV1Vt", 
          "sensorId": "ara", 
          "rawValue": null, 
          "value": 79.64113352318442, 
          "created": "2021-12-20T22:28:12.9846454Z"
        }
      }
    }, 
    {
      "timestamp": "1636738760.0401592", 
      "value": {
        "eventName": "Actuator_LeftArm", 
        "message": {
          "actuatorId": "NBQEA0", 
          "sensorId": "ala", 
          "rawValue": null, 
          "value": 80.78704911344607, 
          "created": "2021-12-20T22:28:13.0002783Z"
        }
      }
    }, 
    {
      "timestamp": "1636738760.0401592", 
      "value": {
        "eventName": "Actuator_HeadPitch", 
        "message": {
          "actuatorId": "Awb61F", 
          "sensorId": "ahp", 
          "rawValue": null, 
          "value": -8.021409131831525, 
          "created": "2021-12-20T22:28:13.0002783Z"
        }
      }
    }, 
    {
      "timestamp": "1636738760.0401592", 
      "value": {
        "eventName": "Actuator_HeadRoll", 
        "message": {
          "actuatorId": "QSygCx", 
          "sensorId": "ahr", 
          "rawValue": null, 
          "value": -16.04281826366305, 
          "created": "2021-12-20T22:28:13.0002783Z"
        }
      }
    }, 
    {
      "timestamp": "1636738760.0401592", 
      "value": {
        "eventName": "Actuator_HeadYaw", 
        "message": {
          "actuatorId": "2ABzJD", 
          "sensorId": "ahy", 
          "rawValue": null, 
          "value": -23.49126960036375, 
          "created": "2021-12-20T22:28:13.0002783Z"
        }
      }
    }, 
    {
      "timestamp": "1636738760.0401592", 
      "value": {
        "eventName": "/Sensors/RTC/IMU", 
        "message": {
          "created": "2021-12-20T22:28:13.0940263Z", 
          "xAcceleration": 0.13, 
          "yaw": 239.09528790809253, 
          "zAcceleration": -9.8, 
          "yawVelocity": 0.0, 
          "yAcceleration": -0.23, 
          "pitch": 1.3178029288008932, 
          "rollVelocity": 0.17188733853924698, 
          "sensorId": "imu", 
          "pitchVelocity": 0.6302535746439055, 
          "roll": 0.7448451336700703
        }
      }
    }, 
    {
      "timestamp": "1636738760.0401592", 
      "value": {
        "eventName": "Actuator_RightArm", 
        "message": {
          "actuatorId": "dYV1Vt", 
          "sensorId": "ara", 
          "rawValue": null, 
          "value": 79.64113352318442, 
          "created": "2021-12-20T22:28:13.1565594Z"
        }
      }
    }, 
    {
      "timestamp": "1636738760.0401592", 
      "value": {
        "eventName": "Actuator_LeftArm", 
        "message": {
          "actuatorId": "NBQEA0", 
          "sensorId": "ala", 
          "rawValue": null, 
          "value": 80.78704911344607, 
          "created": "2021-12-20T22:28:13.1565594Z"
        }
      }
    }, 
    {
      "timestamp": "1636738760.0401592", 
      "value": {
        "eventName": "Actuator_HeadPitch", 
        "message": {
          "actuatorId": "Awb61F", 
          "sensorId": "ahp", 
          "rawValue": null, 
          "value": -5.729577951308232, 
          "created": "2021-12-20T22:28:13.1565594Z"
        }
      }
    }, 
    {
      "timestamp": "1636738760.0401592", 
      "value": {
        "eventName": "Actuator_HeadRoll", 
        "message": {
          "actuatorId": "QSygCx", 
          "sensorId": "ahr", 
          "rawValue": null, 
          "value": -13.178029288008934, 
          "created": "2021-12-20T22:28:13.1565594Z"
        }
      }
    }, 
    {
      "timestamp": "1636738760.0401592", 
      "value": {
        "eventName": "Actuator_HeadYaw", 
        "message": {
          "actuatorId": "2ABzJD", 
          "sensorId": "ahy", 
          "rawValue": null, 
          "value": -21.772396214971284, 
          "created": "2021-12-20T22:28:13.1565594Z"
        }
      }
    }, 
    {
      "timestamp": "1636738760.0401592", 
      "value": {
        "eventName": "/Sensors/RTC/IMU", 
        "message": {
          "created": "2021-12-20T22:28:13.2663062Z", 
          "xAcceleration": 0.13, 
          "yaw": 239.09528790809253, 
          "zAcceleration": -9.8, 
          "yawVelocity": 0.0, 
          "yAcceleration": -0.23, 
          "pitch": 1.3178029288008932, 
          "rollVelocity": 0.40107045659157625, 
          "sensorId": "imu", 
          "pitchVelocity": 0.11459155902616464, 
          "roll": 0.7448451336700703
        }
      }
    }, 
    {
      "timestamp": "1636738760.0401592", 
      "value": {
        "eventName": "Actuator_RightArm", 
        "message": {
          "actuatorId": "dYV1Vt", 
          "sensorId": "ara", 
          "rawValue": null, 
          "value": 66.46310423517549, 
          "created": "2021-12-20T22:28:13.3602769Z"
        }
      }
    }, 
    {
      "timestamp": "1636738760.0401592", 
      "value": {
        "eventName": "Actuator_LeftArm", 
        "message": {
          "actuatorId": "NBQEA0", 
          "sensorId": "ala", 
          "rawValue": null, 
          "value": 80.78704911344607, 
          "created": "2021-12-20T22:28:13.3602769Z"
        }
      }
    }, 
    {
      "timestamp": "1636738760.0401592", 
      "value": {
        "eventName": "Actuator_HeadPitch", 
        "message": {
          "actuatorId": "Awb61F", 
          "sensorId": "ahp", 
          "rawValue": null, 
          "value": -5.729577951308232, 
          "created": "2021-12-20T22:28:13.3602769Z"
        }
      }
    }, 
    {
      "timestamp": "1636738760.0401592", 
      "value": {
        "eventName": "Actuator_HeadRoll", 
        "message": {
          "actuatorId": "QSygCx", 
          "sensorId": "ahr", 
          "rawValue": null, 
          "value": -11.459155902616464, 
          "created": "2021-12-20T22:28:13.3759176Z"
        }
      }
    }, 
    {
      "timestamp": "1636738760.0401592", 
      "value": {
        "eventName": "Actuator_HeadYaw", 
        "message": {
          "actuatorId": "2ABzJD", 
          "sensorId": "ahy", 
          "rawValue": null, 
          "value": -20.626480624709636, 
          "created": "2021-12-20T22:28:13.3759176Z"
        }
      }
    }, 
    {
      "timestamp": "1636738760.0401592", 
      "value": {
        "eventName": "/Sensors/RTC/IMU", 
        "message": {
          "created": "2021-12-20T22:28:13.4541632Z", 
          "xAcceleration": 0.13, 
          "yaw": 239.09528790809253, 
          "zAcceleration": -9.8, 
          "yawVelocity": -0.05729577951308232, 
          "yAcceleration": -0.23, 
          "pitch": 1.3178029288008932, 
          "rollVelocity": 0.0, 
          "sensorId": "imu", 
          "pitchVelocity": 0.0, 
          "roll": 0.7448451336700703
        }
      }
    }, 
    {
      "timestamp": "1636738760.0401592", 
      "value": {
        "eventName": "Actuator_RightArm", 
        "message": {
          "actuatorId": "dYV1Vt", 
          "sensorId": "ara", 
          "rawValue": null, 
          "value": 26.92901637114869, 
          "created": "2021-12-20T22:28:13.5486404Z"
        }
      }
    }, 
    {
      "timestamp": "1636738760.0401592", 
      "value": {
        "eventName": "Actuator_LeftArm", 
        "message": {
          "actuatorId": "NBQEA0", 
          "sensorId": "ala", 
          "rawValue": null, 
          "value": 80.78704911344607, 
          "created": "2021-12-20T22:28:13.5486404Z"
        }
      }
    }, 
    {
      "timestamp": "1636738760.0401592", 
      "value": {
        "eventName": "Actuator_HeadPitch", 
        "message": {
          "actuatorId": "Awb61F", 
          "sensorId": "ahp", 
          "rawValue": null, 
          "value": -5.729577951308232, 
          "created": "2021-12-20T22:28:13.5486404Z"
        }
      }
    }, 
    {
      "timestamp": "1636738760.0401592", 
      "value": {
        "eventName": "Actuator_HeadRoll", 
        "message": {
          "actuatorId": "QSygCx", 
          "sensorId": "ahr", 
          "rawValue": null, 
          "value": -10.886198107485642, 
          "created": "2021-12-20T22:28:13.5642694Z"
        }
      }
    }, 
    {
      "timestamp": "1636738760.0401592", 
      "value": {
        "eventName": "Actuator_HeadYaw", 
        "message": {
          "actuatorId": "2ABzJD", 
          "sensorId": "ahy", 
          "rawValue": null, 
          "value": -18.90760723931717, 
          "created": "2021-12-20T22:28:13.5642694Z"
        }
      }
    }, 
    {
      "timestamp": "1636738760.0401592", 
      "value": {
        "eventName": "/Sensors/RTC/IMU", 
        "message": {
          "created": "2021-12-20T22:28:13.6272317Z", 
          "xAcceleration": 0.13, 
          "yaw": 239.09528790809253, 
          "zAcceleration": -9.8, 
          "yawVelocity": 0.0, 
          "yAcceleration": -0.23, 
          "pitch": 1.3178029288008932, 
          "rollVelocity": 0.0, 
          "sensorId": "imu", 
          "pitchVelocity": 0.0, 
          "roll": 0.7448451336700703
        }
      }
    }, 
    {
      "timestamp": "1636738760.0401592", 
      "value": {
        "eventName": "Actuator_RightArm", 
        "message": {
          "actuatorId": "dYV1Vt", 
          "sensorId": "ara", 
          "rawValue": null, 
          "value": -5.156620156177409, 
          "created": "2021-12-20T22:28:13.7887749Z"
        }
      }
    }, 
    {
      "timestamp": "1636738760.0401592", 
      "value": {
        "eventName": "Actuator_LeftArm", 
        "message": {
          "actuatorId": "NBQEA0", 
          "sensorId": "ala", 
          "rawValue": null, 
          "value": 80.78704911344607, 
          "created": "2021-12-20T22:28:13.8044046Z"
        }
      }
    }, 
    {
      "timestamp": "1636738760.0401592", 
      "value": {
        "eventName": "Actuator_HeadPitch", 
        "message": {
          "actuatorId": "Awb61F", 
          "sensorId": "ahp", 
          "rawValue": null, 
          "value": -5.729577951308232, 
          "created": "2021-12-20T22:28:13.8044046Z"
        }
      }
    }, 
    {
      "timestamp": "1636738760.0401592", 
      "value": {
        "eventName": "Actuator_HeadRoll", 
        "message": {
          "actuatorId": "QSygCx", 
          "sensorId": "ahr", 
          "rawValue": null, 
          "value": -10.313240312354818, 
          "created": "2021-12-20T22:28:13.8044046Z"
        }
      }
    }, 
    {
      "timestamp": "1636738760.0401592", 
      "value": {
        "eventName": "Actuator_HeadYaw", 
        "message": {
          "actuatorId": "2ABzJD", 
          "sensorId": "ahy", 
          "rawValue": null, 
          "value": -17.188733853924695, 
          "created": "2021-12-20T22:28:13.8044046Z"
        }
      }
    }, 
    {
      "timestamp": "1636738760.0401592", 
      "value": {
        "eventName": "/Sensors/RTC/IMU", 
        "message": {
          "created": "2021-12-20T22:28:13.8356523Z", 
          "xAcceleration": 0.13, 
          "yaw": 239.09528790809253, 
          "zAcceleration": -9.8, 
          "yawVelocity": 0.17188733853924698, 
          "yAcceleration": -0.23, 
          "pitch": 1.3178029288008932, 
          "rollVelocity": 0.0, 
          "sensorId": "imu", 
          "pitchVelocity": 0.05729577951308232, 
          "roll": 0.7448451336700703
        }
      }
    }, 
    {
      "timestamp": "1636738760.0401592", 
      "value": {
        "eventName": "Actuator_RightArm", 
        "message": {
          "actuatorId": "dYV1Vt", 
          "sensorId": "ara", 
          "rawValue": null, 
          "value": -4.010704565915763, 
          "created": "2021-12-20T22:28:13.9768125Z"
        }
      }
    }, 
    {
      "timestamp": "1636738760.0401592", 
      "value": {
        "eventName": "Actuator_LeftArm", 
        "message": {
          "actuatorId": "NBQEA0", 
          "sensorId": "ala", 
          "rawValue": null, 
          "value": 80.78704911344607, 
          "created": "2021-12-20T22:28:13.9768125Z"
        }
      }
    }, 
    {
      "timestamp": "1636738760.0401592", 
      "value": {
        "eventName": "Actuator_HeadPitch", 
        "message": {
          "actuatorId": "Awb61F", 
          "sensorId": "ahp", 
          "rawValue": null, 
          "value": -5.729577951308232, 
          "created": "2021-12-20T22:28:13.9768125Z"
        }
      }
    }, 
    {
      "timestamp": "1636738760.0401592", 
      "value": {
        "eventName": "Actuator_HeadRoll", 
        "message": {
          "actuatorId": "QSygCx", 
          "sensorId": "ahr", 
          "rawValue": null, 
          "value": -9.167324722093172, 
          "created": "2021-12-20T22:28:13.9768125Z"
        }
      }
    }, 
    {
      "timestamp": "1636738760.0401592", 
      "value": {
        "eventName": "Actuator_HeadYaw", 
        "message": {
          "actuatorId": "2ABzJD", 
          "sensorId": "ahy", 
          "rawValue": null, 
          "value": -15.469860468532227, 
          "created": "2021-12-20T22:28:13.9924453Z"
        }
      }
    }, 
    {
      "timestamp": "1636738760.0401592", 
      "value": {
        "eventName": "/Sensors/RTC/IMU", 
        "message": {
          "created": "2021-12-20T22:28:13.9924453Z", 
          "xAcceleration": 0.13, 
          "yaw": 239.09528790809253, 
          "zAcceleration": -9.8, 
          "yawVelocity": 0.0, 
          "yAcceleration": -0.23, 
          "pitch": 1.3178029288008932, 
          "rollVelocity": 0.0, 
          "sensorId": "imu", 
          "pitchVelocity": -0.11459155902616464, 
          "roll": 0.7448451336700703
        }
      }
    }, 
    {
      "timestamp": "1636738760.0401592", 
      "value": {
        "eventName": "Actuator_RightArm", 
        "message": {
          "actuatorId": "dYV1Vt", 
          "sensorId": "ara", 
          "rawValue": null, 
          "value": -4.010704565915763, 
          "created": "2021-12-20T22:28:14.1647205Z"
        }
      }
    }, 
    {
      "timestamp": "1636738760.0401592", 
      "value": {
        "eventName": "Actuator_LeftArm", 
        "message": {
          "actuatorId": "NBQEA0", 
          "sensorId": "ala", 
          "rawValue": null, 
          "value": 80.78704911344607, 
          "created": "2021-12-20T22:28:14.1647205Z"
        }
      }
    }, 
    {
      "timestamp": "1636738760.0401592", 
      "value": {
        "eventName": "Actuator_HeadPitch", 
        "message": {
          "actuatorId": "Awb61F", 
          "sensorId": "ahp", 
          "rawValue": null, 
          "value": -4.583662361046586, 
          "created": "2021-12-20T22:28:14.1647205Z"
        }
      }
    }, 
    {
      "timestamp": "1636738760.0401592", 
      "value": {
        "eventName": "Actuator_HeadRoll", 
        "message": {
          "actuatorId": "QSygCx", 
          "sensorId": "ahr", 
          "rawValue": null, 
          "value": -8.021409131831525, 
          "created": "2021-12-20T22:28:14.1647205Z"
        }
      }
    }, 
    {
      "timestamp": "1636738760.0401592", 
      "value": {
        "eventName": "Actuator_HeadYaw", 
        "message": {
          "actuatorId": "2ABzJD", 
          "sensorId": "ahy", 
          "rawValue": null, 
          "value": -13.750987083139757, 
          "created": "2021-12-20T22:28:14.1803512Z"
        }
      }
    }, 
    {
      "timestamp": "1636738760.0401592", 
      "value": {
        "eventName": "/Sensors/RTC/IMU", 
        "message": {
          "created": "2021-12-20T22:28:14.1803512Z", 
          "xAcceleration": 0.13, 
          "yaw": 239.09528790809253, 
          "zAcceleration": -9.8, 
          "yawVelocity": -0.05729577951308232, 
          "yAcceleration": -0.23, 
          "pitch": 1.3178029288008932, 
          "rollVelocity": 0.05729577951308232, 
          "sensorId": "imu", 
          "pitchVelocity": 0.6302535746439055, 
          "roll": 0.7448451336700703
        }
      }
    }, 
    {
      "timestamp": "1636738760.0401592", 
      "value": {
        "eventName": "/Sensors/RTC/IMU", 
        "message": {
          "created": "2021-12-20T22:28:14.3213212Z", 
          "xAcceleration": 0.13, 
          "yaw": 239.09528790809253, 
          "zAcceleration": -9.8, 
          "yawVelocity": -0.17188733853924698, 
          "yAcceleration": -0.23, 
          "pitch": 1.3178029288008932, 
          "rollVelocity": 0.0, 
          "sensorId": "imu", 
          "pitchVelocity": -0.45836623610465854, 
          "roll": 0.7448451336700703
        }
      }
    }, 
    {
      "timestamp": "1636738760.0401592", 
      "value": {
        "eventName": "Actuator_RightArm", 
        "message": {
          "actuatorId": "dYV1Vt", 
          "sensorId": "ara", 
          "rawValue": null, 
          "value": -2.864788975654116, 
          "created": "2021-12-20T22:28:14.3838792Z"
        }
      }
    }, 
    {
      "timestamp": "1636738760.0401592", 
      "value": {
        "eventName": "Actuator_LeftArm", 
        "message": {
          "actuatorId": "NBQEA0", 
          "sensorId": "ala", 
          "rawValue": null, 
          "value": 80.78704911344607, 
          "created": "2021-12-20T22:28:14.3838792Z"
        }
      }
    }, 
    {
      "timestamp": "1636738760.0401592", 
      "value": {
        "eventName": "Actuator_HeadPitch", 
        "message": {
          "actuatorId": "Awb61F", 
          "sensorId": "ahp", 
          "rawValue": null, 
          "value": -3.437746770784939, 
          "created": "2021-12-20T22:28:14.3838792Z"
        }
      }
    }, 
    {
      "timestamp": "1636738760.0401592", 
      "value": {
        "eventName": "Actuator_HeadRoll", 
        "message": {
          "actuatorId": "QSygCx", 
          "sensorId": "ahr", 
          "rawValue": null, 
          "value": -6.875493541569878, 
          "created": "2021-12-20T22:28:14.3838792Z"
        }
      }
    }, 
    {
      "timestamp": "1636738760.0401592", 
      "value": {
        "eventName": "Actuator_HeadYaw", 
        "message": {
          "actuatorId": "2ABzJD", 
          "sensorId": "ahy", 
          "rawValue": null, 
          "value": -13.178029288008934, 
          "created": "2021-12-20T22:28:14.3995049Z"
        }
      }
    }, 
    {
      "timestamp": "1636738760.0401592", 
      "value": {
        "eventName": "/Sensors/RTC/IMU", 
        "message": {
          "created": "2021-12-20T22:28:14.5115504Z", 
          "xAcceleration": 0.13, 
          "yaw": 239.09528790809253, 
          "zAcceleration": -9.8, 
          "yawVelocity": 0.0, 
          "yAcceleration": -0.23, 
          "pitch": 1.3178029288008932, 
          "rollVelocity": 0.0, 
          "sensorId": "imu", 
          "pitchVelocity": 0.45836623610465854, 
          "roll": 0.7448451336700703
        }
      }
    }, 
    {
      "timestamp": "1636738760.0401592", 
      "value": {
        "eventName": "Actuator_RightArm", 
        "message": {
          "actuatorId": "dYV1Vt", 
          "sensorId": "ara", 
          "rawValue": null, 
          "value": 14.896902673401405, 
          "created": "2021-12-20T22:28:14.5584251Z"
        }
      }
    }, 
    {
      "timestamp": "1636738760.0401592", 
      "value": {
        "eventName": "Actuator_LeftArm", 
        "message": {
          "actuatorId": "NBQEA0", 
          "sensorId": "ala", 
          "rawValue": null, 
          "value": 80.78704911344607, 
          "created": "2021-12-20T22:28:14.5584251Z"
        }
      }
    }, 
    {
      "timestamp": "1636738760.0401592", 
      "value": {
        "eventName": "Actuator_HeadPitch", 
        "message": {
          "actuatorId": "Awb61F", 
          "sensorId": "ahp", 
          "rawValue": null, 
          "value": -2.291831180523293, 
          "created": "2021-12-20T22:28:14.5584251Z"
        }
      }
    }, 
    {
      "timestamp": "1636738760.0401592", 
      "value": {
        "eventName": "Actuator_HeadRoll", 
        "message": {
          "actuatorId": "QSygCx", 
          "sensorId": "ahr", 
          "rawValue": null, 
          "value": -7.448451336700702, 
          "created": "2021-12-20T22:28:14.5584251Z"
        }
      }
    }, 
    {
      "timestamp": "1636738760.0401592", 
      "value": {
        "eventName": "Actuator_HeadYaw", 
        "message": {
          "actuatorId": "2ABzJD", 
          "sensorId": "ahy", 
          "rawValue": null, 
          "value": -13.178029288008934, 
          "created": "2021-12-20T22:28:14.5584251Z"
        }
      }
    }, 
    {
      "timestamp": "1636738760.0401592", 
      "value": {
        "eventName": "/Sensors/RTC/IMU", 
        "message": {
          "created": "2021-12-20T22:28:14.6729444Z", 
          "xAcceleration": 0.13, 
          "yaw": 239.09528790809253, 
          "zAcceleration": -9.8, 
          "yawVelocity": 0.0, 
          "yAcceleration": -0.24, 
          "pitch": 1.3750987083139758, 
          "rollVelocity": 0.0, 
          "sensorId": "imu", 
          "pitchVelocity": 0.0, 
          "roll": 0.7448451336700703
        }
      }
    }, 
    {
      "timestamp": "1636738760.0401592", 
      "value": {
        "eventName": "Actuator_RightArm", 
        "message": {
          "actuatorId": "dYV1Vt", 
          "sensorId": "ara", 
          "rawValue": null, 
          "value": 60.73352628386726, 
          "created": "2021-12-20T22:28:14.7843271Z"
        }
      }
    }, 
    {
      "timestamp": "1636738760.0401592", 
      "value": {
        "eventName": "Actuator_LeftArm", 
        "message": {
          "actuatorId": "NBQEA0", 
          "sensorId": "ala", 
          "rawValue": null, 
          "value": 80.78704911344607, 
          "created": "2021-12-20T22:28:14.7843271Z"
        }
      }
    }, 
    {
      "timestamp": "1636738760.0401592", 
      "value": {
        "eventName": "Actuator_HeadPitch", 
        "message": {
          "actuatorId": "Awb61F", 
          "sensorId": "ahp", 
          "rawValue": null, 
          "value": -2.291831180523293, 
          "created": "2021-12-20T22:28:14.7843271Z"
        }
      }
    }, 
    {
      "timestamp": "1636738760.0401592", 
      "value": {
        "eventName": "Actuator_HeadRoll", 
        "message": {
          "actuatorId": "QSygCx", 
          "sensorId": "ahr", 
          "rawValue": null, 
          "value": -7.448451336700702, 
          "created": "2021-12-20T22:28:14.7843271Z"
        }
      }
    }, 
    {
      "timestamp": "1636738760.0401592", 
      "value": {
        "eventName": "Actuator_HeadYaw", 
        "message": {
          "actuatorId": "2ABzJD", 
          "sensorId": "ahy", 
          "rawValue": null, 
          "value": -13.178029288008934, 
          "created": "2021-12-20T22:28:14.7843271Z"
        }
      }
    }, 
    {
      "timestamp": "1636738760.0401592", 
      "value": {
        "eventName": "/Sensors/RTC/IMU", 
        "message": {
          "created": "2021-12-20T22:28:14.8470471Z", 
          "xAcceleration": 0.13, 
          "yaw": 239.09528790809253, 
          "zAcceleration": -9.8, 
          "yawVelocity": 0.0, 
          "yAcceleration": -0.24, 
          "pitch": 1.3750987083139758, 
          "rollVelocity": 0.11459155902616464, 
          "sensorId": "imu", 
          "pitchVelocity": -0.05729577951308232, 
          "roll": 0.7448451336700703
        }
      }
    }, 
    {
      "timestamp": "1636738760.0401592", 
      "value": {
        "eventName": "Actuator_RightArm", 
        "message": {
          "actuatorId": "dYV1Vt", 
          "sensorId": "ara", 
          "rawValue": null, 
          "value": 101.98648753328652, 
          "created": "2021-12-20T22:28:14.9551383Z"
        }
      }
    }, 
    {
      "timestamp": "1636738760.0401592", 
      "value": {
        "eventName": "Actuator_LeftArm", 
        "message": {
          "actuatorId": "NBQEA0", 
          "sensorId": "ala", 
          "rawValue": null, 
          "value": 80.78704911344607, 
          "created": "2021-12-20T22:28:14.9551383Z"
        }
      }
    }, 
    {
      "timestamp": "1636738760.0401592", 
      "value": {
        "eventName": "Actuator_HeadPitch", 
        "message": {
          "actuatorId": "Awb61F", 
          "sensorId": "ahp", 
          "rawValue": null, 
          "value": -2.291831180523293, 
          "created": "2021-12-20T22:28:14.9551383Z"
        }
      }
    }, 
    {
      "timestamp": "1636738760.0401592", 
      "value": {
        "eventName": "Actuator_HeadRoll", 
        "message": {
          "actuatorId": "QSygCx", 
          "sensorId": "ahr", 
          "rawValue": null, 
          "value": -7.448451336700702, 
          "created": "2021-12-20T22:28:14.9551383Z"
        }
      }
    }, 
    {
      "timestamp": "1636738760.0401592", 
      "value": {
        "eventName": "Actuator_HeadYaw", 
        "message": {
          "actuatorId": "2ABzJD", 
          "sensorId": "ahy", 
          "rawValue": null, 
          "value": -12.032113697747286, 
          "created": "2021-12-20T22:28:14.9551383Z"
        }
      }
    }, 
    {
      "timestamp": "1636738760.0401592", 
      "value": {
        "eventName": "/Sensors/RTC/IMU", 
        "message": {
          "created": "2021-12-20T22:28:15.072325Z", 
          "xAcceleration": 0.13, 
          "yaw": 239.09528790809253, 
          "zAcceleration": -9.8, 
          "yawVelocity": -0.05729577951308232, 
          "yAcceleration": -0.24, 
          "pitch": 1.3750987083139758, 
          "rollVelocity": 0.0, 
          "sensorId": "imu", 
          "pitchVelocity": 0.0, 
          "roll": 0.7448451336700703
        }
      }
    }, 
    {
      "timestamp": "1636738760.0401592", 
      "value": {
        "eventName": "Actuator_RightArm", 
        "message": {
          "actuatorId": "dYV1Vt", 
          "sensorId": "ara", 
          "rawValue": null, 
          "value": 83.07888029396936, 
          "created": "2021-12-20T22:28:15.1662957Z"
        }
      }
    }, 
    {
      "timestamp": "1636738760.0401592", 
      "value": {
        "eventName": "Actuator_LeftArm", 
        "message": {
          "actuatorId": "NBQEA0", 
          "sensorId": "ala", 
          "rawValue": null, 
          "value": 80.78704911344607, 
          "created": "2021-12-20T22:28:15.1662957Z"
        }
      }
    }, 
    {
      "timestamp": "1636738760.0401592", 
      "value": {
        "eventName": "Actuator_HeadPitch", 
        "message": {
          "actuatorId": "Awb61F", 
          "sensorId": "ahp", 
          "rawValue": null, 
          "value": -2.291831180523293, 
          "created": "2021-12-20T22:28:15.1662957Z"
        }
      }
    }, 
    {
      "timestamp": "1636738760.0401592", 
      "value": {
        "eventName": "Actuator_HeadRoll", 
        "message": {
          "actuatorId": "QSygCx", 
          "sensorId": "ahr", 
          "rawValue": null, 
          "value": -7.448451336700702, 
          "created": "2021-12-20T22:28:15.1819435Z"
        }
      }
    }, 
    {
      "timestamp": "1636738760.0401592", 
      "value": {
        "eventName": "Actuator_HeadYaw", 
        "message": {
          "actuatorId": "2ABzJD", 
          "sensorId": "ahy", 
          "rawValue": null, 
          "value": -10.886198107485642, 
          "created": "2021-12-20T22:28:15.1819435Z"
        }
      }
    }, 
    {
      "timestamp": "1636738760.0401592", 
      "value": {
        "eventName": "/Sensors/RTC/IMU", 
        "message": {
          "created": "2021-12-20T22:28:15.1975654Z", 
          "xAcceleration": 0.13, 
          "yaw": 239.09528790809253, 
          "zAcceleration": -9.8, 
          "yawVelocity": 0.0, 
          "yAcceleration": -0.24, 
          "pitch": 1.3750987083139758, 
          "rollVelocity": 0.0, 
          "sensorId": "imu", 
          "pitchVelocity": -0.05729577951308232, 
          "roll": 0.7448451336700703
        }
      }
    }, 
    {
      "timestamp": "1636738760.0401592", 
      "value": {
        "eventName": "Actuator_RightArm", 
        "message": {
          "actuatorId": "dYV1Vt", 
          "sensorId": "ara", 
          "rawValue": null, 
          "value": 79.0681757280536, 
          "created": "2021-12-20T22:28:15.3991784Z"
        }
      }
    }, 
    {
      "timestamp": "1636738760.0401592", 
      "value": {
        "eventName": "Actuator_LeftArm", 
        "message": {
          "actuatorId": "NBQEA0", 
          "sensorId": "ala", 
          "rawValue": null, 
          "value": 80.78704911344607, 
          "created": "2021-12-20T22:28:15.3991784Z"
        }
      }
    }, 
    {
      "timestamp": "1636738760.0401592", 
      "value": {
        "eventName": "Actuator_HeadPitch", 
        "message": {
          "actuatorId": "Awb61F", 
          "sensorId": "ahp", 
          "rawValue": null, 
          "value": -2.291831180523293, 
          "created": "2021-12-20T22:28:15.3991784Z"
        }
      }
    }, 
    {
      "timestamp": "1636738760.0401592", 
      "value": {
        "eventName": "Actuator_HeadRoll", 
        "message": {
          "actuatorId": "QSygCx", 
          "sensorId": "ahr", 
          "rawValue": null, 
          "value": -7.448451336700702, 
          "created": "2021-12-20T22:28:15.3991784Z"
        }
      }
    }, 
    {
      "timestamp": "1636738760.0401592", 
      "value": {
        "eventName": "Actuator_HeadYaw", 
        "message": {
          "actuatorId": "2ABzJD", 
          "sensorId": "ahy", 
          "rawValue": null, 
          "value": -10.313240312354818, 
          "created": "2021-12-20T22:28:15.3991784Z"
        }
      }
    }, 
    {
      "timestamp": "1636738760.0401592", 
      "value": {
        "eventName": "/Sensors/RTC/IMU", 
        "message": {
          "created": "2021-12-20T22:28:15.4148057Z", 
          "xAcceleration": 0.13, 
          "yaw": 239.09528790809253, 
          "zAcceleration": -9.8, 
          "yawVelocity": 0.0, 
          "yAcceleration": -0.24, 
          "pitch": 1.3750987083139758, 
          "rollVelocity": 0.0, 
          "sensorId": "imu", 
          "pitchVelocity": 0.0, 
          "roll": 0.7448451336700703
        }
      }
    }, 
    {
      "timestamp": "1636738760.0401592", 
      "value": {
        "eventName": "Actuator_RightArm", 
        "message": {
          "actuatorId": "dYV1Vt", 
          "sensorId": "ara", 
          "rawValue": null, 
          "value": 79.0681757280536, 
          "created": "2021-12-20T22:28:15.5873097Z"
        }
      }
    }, 
    {
      "timestamp": "1636738760.0401592", 
      "value": {
        "eventName": "Actuator_LeftArm", 
        "message": {
          "actuatorId": "NBQEA0", 
          "sensorId": "ala", 
          "rawValue": null, 
          "value": 79.64113352318442, 
          "created": "2021-12-20T22:28:15.5873097Z"
        }
      }
    }, 
    {
      "timestamp": "1636738760.0401592", 
      "value": {
        "eventName": "Actuator_HeadPitch", 
        "message": {
          "actuatorId": "Awb61F", 
          "sensorId": "ahp", 
          "rawValue": null, 
          "value": -2.291831180523293, 
          "created": "2021-12-20T22:28:15.5873097Z"
        }
      }
    }, 
    {
      "timestamp": "1636738760.0401592", 
      "value": {
        "eventName": "Actuator_HeadRoll", 
        "message": {
          "actuatorId": "QSygCx", 
          "sensorId": "ahr", 
          "rawValue": null, 
          "value": -7.448451336700702, 
          "created": "2021-12-20T22:28:15.602931Z"
        }
      }
    }, 
    {
      "timestamp": "1636738760.0401592", 
      "value": {
        "eventName": "Actuator_HeadYaw", 
        "message": {
          "actuatorId": "2ABzJD", 
          "sensorId": "ahy", 
          "rawValue": null, 
          "value": -9.167324722093172, 
          "created": "2021-12-20T22:28:15.602931Z"
        }
      }
    }, 
    {
      "timestamp": "1636738760.0401592", 
      "value": {
        "eventName": "/Sensors/RTC/IMU", 
        "message": {
          "created": "2021-12-20T22:28:15.602931Z", 
          "xAcceleration": 0.13, 
          "yaw": 239.09528790809253, 
          "zAcceleration": -9.8, 
          "yawVelocity": 0.0, 
          "yAcceleration": -0.24, 
          "pitch": 1.3750987083139758, 
          "rollVelocity": -0.05729577951308232, 
          "sensorId": "imu", 
          "pitchVelocity": 0.0, 
          "roll": 0.7448451336700703
        }
      }
    }, 
    {
      "timestamp": "1636738760.0401592", 
      "value": {
        "eventName": "/Sensors/RTC/IMU", 
        "message": {
          "created": "2021-12-20T22:28:15.7281941Z", 
          "xAcceleration": 0.13, 
          "yaw": 239.09528790809253, 
          "zAcceleration": -9.8, 
          "yawVelocity": 0.05729577951308232, 
          "yAcceleration": -0.24, 
          "pitch": 1.3750987083139758, 
          "rollVelocity": -0.11459155902616464, 
          "sensorId": "imu", 
          "pitchVelocity": -0.05729577951308232, 
          "roll": 0.7448451336700703
        }
      }
    }, 
    {
      "timestamp": "1636738760.0401592", 
      "value": {
        "eventName": "Actuator_RightArm", 
        "message": {
          "actuatorId": "dYV1Vt", 
          "sensorId": "ara", 
          "rawValue": null, 
          "value": 79.0681757280536, 
          "created": "2021-12-20T22:28:15.7594535Z"
        }
      }
    }, 
    {
      "timestamp": "1636738760.0401592", 
      "value": {
        "eventName": "Actuator_LeftArm", 
        "message": {
          "actuatorId": "NBQEA0", 
          "sensorId": "ala", 
          "rawValue": null, 
          "value": 75.63042895726868, 
          "created": "2021-12-20T22:28:15.7594535Z"
        }
      }
    }, 
    {
      "timestamp": "1636738760.0401592", 
      "value": {
        "eventName": "Actuator_HeadPitch", 
        "message": {
          "actuatorId": "Awb61F", 
          "sensorId": "ahp", 
          "rawValue": null, 
          "value": -2.291831180523293, 
          "created": "2021-12-20T22:28:15.7594535Z"
        }
      }
    }, 
    {
      "timestamp": "1636738760.0401592", 
      "value": {
        "eventName": "Actuator_HeadRoll", 
        "message": {
          "actuatorId": "QSygCx", 
          "sensorId": "ahr", 
          "rawValue": null, 
          "value": -7.448451336700702, 
          "created": "2021-12-20T22:28:15.7594535Z"
        }
      }
    }, 
    {
      "timestamp": "1636738760.0401592", 
      "value": {
        "eventName": "Actuator_HeadYaw", 
        "message": {
          "actuatorId": "2ABzJD", 
          "sensorId": "ahy", 
          "rawValue": null, 
          "value": -9.167324722093172, 
          "created": "2021-12-20T22:28:15.7594535Z"
        }
      }
    }, 
    {
      "timestamp": "1636738760.0401592", 
      "value": {
        "eventName": "/Sensors/RTC/IMU", 
        "message": {
          "created": "2021-12-20T22:28:15.9033426Z", 
          "xAcceleration": 0.13, 
          "yaw": 239.09528790809253, 
          "zAcceleration": -9.8, 
          "yawVelocity": -0.05729577951308232, 
          "yAcceleration": -0.24, 
          "pitch": 1.3750987083139758, 
          "rollVelocity": 0.0, 
          "sensorId": "imu", 
          "pitchVelocity": -0.11459155902616464, 
          "roll": 0.7448451336700703
        }
      }
    }, 
    {
      "timestamp": "1636738760.0401592", 
      "value": {
        "eventName": "Actuator_RightArm", 
        "message": {
          "actuatorId": "dYV1Vt", 
          "sensorId": "ara", 
          "rawValue": null, 
          "value": 79.0681757280536, 
          "created": "2021-12-20T22:28:15.9502403Z"
        }
      }
    }, 
    {
      "timestamp": "1636738760.0401592", 
      "value": {
        "eventName": "Actuator_LeftArm", 
        "message": {
          "actuatorId": "NBQEA0", 
          "sensorId": "ala", 
          "rawValue": null, 
          "value": 75.63042895726868, 
          "created": "2021-12-20T22:28:15.9502403Z"
        }
      }
    }, 
    {
      "timestamp": "1636738760.0401592", 
      "value": {
        "eventName": "Actuator_HeadPitch", 
        "message": {
          "actuatorId": "Awb61F", 
          "sensorId": "ahp", 
          "rawValue": null, 
          "value": -1.7188733853924696, 
          "created": "2021-12-20T22:28:15.9502403Z"
        }
      }
    }, 
    {
      "timestamp": "1636738760.0401592", 
      "value": {
        "eventName": "Actuator_HeadRoll", 
        "message": {
          "actuatorId": "QSygCx", 
          "sensorId": "ahr", 
          "rawValue": null, 
          "value": -7.448451336700702, 
          "created": "2021-12-20T22:28:15.9502403Z"
        }
      }
    }, 
    {
      "timestamp": "1636738760.0401592", 
      "value": {
        "eventName": "Actuator_HeadYaw", 
        "message": {
          "actuatorId": "2ABzJD", 
          "sensorId": "ahy", 
          "rawValue": null, 
          "value": -9.167324722093172, 
          "created": "2021-12-20T22:28:15.9502403Z"
        }
      }
    }, 
    {
      "timestamp": "1636738760.0401592", 
      "value": {
        "eventName": "/Sensors/RTC/IMU", 
        "message": {
          "created": "2021-12-20T22:28:16.0781352Z", 
          "xAcceleration": 0.13, 
          "yaw": 239.09528790809253, 
          "zAcceleration": -9.8, 
          "yawVelocity": -0.11459155902616464, 
          "yAcceleration": -0.24, 
          "pitch": 1.3750987083139758, 
          "rollVelocity": 0.0, 
          "sensorId": "imu", 
          "pitchVelocity": -0.17188733853924698, 
          "roll": 0.7448451336700703
        }
      }
    }, 
    {
      "timestamp": "1636738760.0401592", 
      "value": {
        "eventName": "Actuator_RightArm", 
        "message": {
          "actuatorId": "dYV1Vt", 
          "sensorId": "ara", 
          "rawValue": null, 
          "value": 79.0681757280536, 
          "created": "2021-12-20T22:28:16.2175819Z"
        }
      }
    }, 
    {
      "timestamp": "1636738760.0401592", 
      "value": {
        "eventName": "Actuator_LeftArm", 
        "message": {
          "actuatorId": "NBQEA0", 
          "sensorId": "ala", 
          "rawValue": null, 
          "value": 77.34930234266115, 
          "created": "2021-12-20T22:28:16.2175819Z"
        }
      }
    }, 
    {
      "timestamp": "1636738760.0401592", 
      "value": {
        "eventName": "Actuator_HeadPitch", 
        "message": {
          "actuatorId": "Awb61F", 
          "sensorId": "ahp", 
          "rawValue": null, 
          "value": -1.7188733853924696, 
          "created": "2021-12-20T22:28:16.2175819Z"
        }
      }
    }, 
    {
      "timestamp": "1636738760.0401592", 
      "value": {
        "eventName": "Actuator_HeadRoll", 
        "message": {
          "actuatorId": "QSygCx", 
          "sensorId": "ahr", 
          "rawValue": null, 
          "value": -7.448451336700702, 
          "created": "2021-12-20T22:28:16.2175819Z"
        }
      }
    }, 
    {
      "timestamp": "1636738760.0401592", 
      "value": {
        "eventName": "Actuator_HeadYaw", 
        "message": {
          "actuatorId": "2ABzJD", 
          "sensorId": "ahy", 
          "rawValue": null, 
          "value": -8.594366926962348, 
          "created": "2021-12-20T22:28:16.2175819Z"
        }
      }
    }, 
    {
      "timestamp": "1636738760.0401592", 
      "value": {
        "eventName": "/Sensors/RTC/IMU", 
        "message": {
          "created": "2021-12-20T22:28:16.2488359Z", 
          "xAcceleration": 0.13, 
          "yaw": 239.09528790809253, 
          "zAcceleration": -9.8, 
          "yawVelocity": 0.0, 
          "yAcceleration": -0.24, 
          "pitch": 1.3750987083139758, 
          "rollVelocity": -0.05729577951308232, 
          "sensorId": "imu", 
          "pitchVelocity": 0.0, 
          "roll": 0.7448451336700703
        }
      }
    }, 
    {
      "timestamp": "1636738760.0401592", 
      "value": {
        "eventName": "Actuator_RightArm", 
        "message": {
          "actuatorId": "dYV1Vt", 
          "sensorId": "ara", 
          "rawValue": null, 
          "value": 79.0681757280536, 
          "created": "2021-12-20T22:28:16.3522775Z"
        }
      }
    }, 
    {
      "timestamp": "1636738760.0401592", 
      "value": {
        "eventName": "Actuator_LeftArm", 
        "message": {
          "actuatorId": "NBQEA0", 
          "sensorId": "ala", 
          "rawValue": null, 
          "value": 80.21409131831524, 
          "created": "2021-12-20T22:28:16.3679051Z"
        }
      }
    }, 
    {
      "timestamp": "1636738760.0401592", 
      "value": {
        "eventName": "Actuator_HeadPitch", 
        "message": {
          "actuatorId": "Awb61F", 
          "sensorId": "ahp", 
          "rawValue": null, 
          "value": -1.7188733853924696, 
          "created": "2021-12-20T22:28:16.3679051Z"
        }
      }
    }, 
    {
      "timestamp": "1636738760.0401592", 
      "value": {
        "eventName": "Actuator_HeadRoll", 
        "message": {
          "actuatorId": "QSygCx", 
          "sensorId": "ahr", 
          "rawValue": null, 
          "value": -7.448451336700702, 
          "created": "2021-12-20T22:28:16.3679051Z"
        }
      }
    }, 
    {
      "timestamp": "1636738760.0401592", 
      "value": {
        "eventName": "Actuator_HeadYaw", 
        "message": {
          "actuatorId": "2ABzJD", 
          "sensorId": "ahy", 
          "rawValue": null, 
          "value": -7.448451336700702, 
          "created": "2021-12-20T22:28:16.3679051Z"
        }
      }
    }, 
    {
      "timestamp": "1636738760.0401592", 
      "value": {
        "eventName": "/Sensors/RTC/IMU", 
        "message": {
          "created": "2021-12-20T22:28:16.4692944Z", 
          "xAcceleration": 0.13, 
          "yaw": 239.09528790809253, 
          "zAcceleration": -9.8, 
          "yawVelocity": 0.0, 
          "yAcceleration": -0.24, 
          "pitch": 1.3750987083139758, 
          "rollVelocity": 0.0, 
          "sensorId": "imu", 
          "pitchVelocity": 0.0, 
          "roll": 0.7448451336700703
        }
      }
    }
  ]
}